kspaces/EM.py
kspaces/__init__.py
kspaces/affine_subspace_.py
kspaces/generate_.py
kspaces/model_selection_.py
kspaces/plotting.py
kspaces-0.1.5.dist-info/licenses/LICENSE
kspaces-0.1.5.dist-info/METADATA
kspaces-0.1.5.dist-info/WHEEL
kspaces-0.1.5.dist-info/top_level.txt
kspaces-0.1.5.dist-info/RECORD
