Metadata-Version: 2.4
Name: kspaces
Version: 0.1.5
Summary: Mixtures of latent variable models for dimensionality reduction, subspace learning, and clustering in biological data analysis.
Author-email: Nicholas Markarian <nmarkari@usc.edu>
Maintainer-email: Nicholas Markarian <nmarkari@usc.edu>
License: BSD 2-Clause License
Project-URL: Homepage, https://github.com/pachterlab/k-spaces/
Keywords: k-spaces,kspaces,bioinformatics,subspace,dimension reduction,clustering,RNA-seq
Classifier: Intended Audience :: Science/Research
Classifier: License :: OSI Approved :: BSD License
Classifier: Operating System :: OS Independent
Classifier: Programming Language :: Python :: 3.10
Classifier: Programming Language :: Python :: 3.11
Classifier: Programming Language :: Python :: 3.12
Classifier: Topic :: Scientific/Engineering :: Bio-Informatics
Requires-Python: >=3.10
License-File: LICENSE
Requires-Dist: numpy>=1.24.3
Requires-Dist: matplotlib>=3.7.2
Requires-Dist: scipy>=1.11.4
Requires-Dist: scikit-learn>=1.3.0
Requires-Dist: joblib>=1.2.0
Dynamic: license-file
